brainiak/_version.py
brainiak/isc.py
brainiak/io.py
brainiak/__init__.py
brainiak/image.py
brainiak/searchlight/searchlight.py
brainiak/searchlight/__init__.py
brainiak/hyperparamopt/__init__.py
brainiak/hyperparamopt/hpo.py
brainiak/funcalign/fastsrm.py
brainiak/funcalign/sssrm.py
brainiak/funcalign/__init__.py
brainiak/funcalign/rsrm.py
brainiak/funcalign/srm.py
brainiak/matnormal/covs.py
brainiak/matnormal/regression.py
brainiak/matnormal/matnormal_likelihoods.py
brainiak/matnormal/__init__.py
brainiak/matnormal/mnrsa.py
brainiak/matnormal/utils.py
brainiak/factoranalysis/tfa_extension.cpython-39-darwin.so
brainiak/factoranalysis/tfa.py
brainiak/factoranalysis/CMakeLists.txt
brainiak/factoranalysis/htfa.py
brainiak/factoranalysis/__init__.py
brainiak/factoranalysis/tfa_extension.cpp
brainiak/fcma/mvpa_voxelselector.py
brainiak/fcma/classifier.py
brainiak/fcma/CMakeLists.txt
brainiak/fcma/cython_blas.cpython-39-darwin.so
brainiak/fcma/util.py
brainiak/fcma/__init__.py
brainiak/fcma/preprocessing.py
brainiak/fcma/cython_blas.pyx
brainiak/fcma/fcma_extension.cpython-39-darwin.so
brainiak/fcma/voxelselector.py
brainiak/fcma/src/fcma_extension.cc
brainiak/reprsimil/__init__.py
brainiak/reprsimil/brsa.py
brainiak/utils/fmrisim_real_time_generator.py
brainiak/utils/__init__.py
brainiak/utils/fmrisim.py
brainiak/utils/utils.py
brainiak/utils/kronecker_solvers.py
brainiak/utils/sim_parameters/sub_template.nii.gz
brainiak/utils/sim_parameters/ROI_A.nii.gz
brainiak/utils/sim_parameters/sub_noise_dict.txt
brainiak/utils/sim_parameters/grey_matter_mask.npy
brainiak/utils/sim_parameters/ROI_B.nii.gz
brainiak/reconstruct/iem.py
brainiak/reconstruct/__init__.py
brainiak/.dylibs/libomp.dylib
brainiak/eventseg/_utils.pyx
brainiak/eventseg/event.py
brainiak/eventseg/CMakeLists.txt
brainiak/eventseg/__init__.py
brainiak/eventseg/_utils.cpython-39-darwin.so
brainiak-0.12.dist-info/RECORD
brainiak-0.12.dist-info/WHEEL
brainiak-0.12.dist-info/METADATA
brainiak-0.12.dist-info/licenses/LICENSE
