Metadata-Version: 2.1
Name: brainiak
Version: 0.12
Summary: Brain Imaging Analysis Kit
Keywords: neuroscience,algorithm,fMRI,distributed,scalable
Author-Email: Princeton Neuroscience Institute and Intel Corporation <mihai.capota@intel.com>
Maintainer-Email: Mihai Capota <mihai.capota@intel.com>
License:                                  Apache License
Classifier: Development Status :: 5 - Production/Stable
Classifier: Intended Audience :: Developers
Classifier: Intended Audience :: Information Technology
Classifier: Intended Audience :: Science/Research
Classifier: License :: OSI Approved :: Apache Software License
Classifier: Operating System :: MacOS
Classifier: Operating System :: Microsoft :: Windows
Classifier: Operating System :: POSIX
Classifier: Operating System :: Unix
Classifier: Programming Language :: C++
Classifier: Programming Language :: Python
Classifier: Programming Language :: Python :: 3
Classifier: Programming Language :: Python :: 3 :: Only
Classifier: Programming Language :: Python :: 3.5
Classifier: Programming Language :: Python :: 3.6
Classifier: Programming Language :: Python :: 3.7
Classifier: Programming Language :: Python :: 3.8
Classifier: Programming Language :: Python :: 3.9
Classifier: Programming Language :: Python :: 3.10
Classifier: Programming Language :: Python :: Implementation :: CPython
Classifier: Topic :: Scientific/Engineering
Classifier: Topic :: Scientific/Engineering :: Information Analysis
Classifier: Topic :: Scientific/Engineering :: Mathematics
Classifier: Topic :: Scientific/Engineering :: Medical Science Apps.
Classifier: Topic :: Scientific/Engineering :: Bio-Informatics
Classifier: Topic :: Software Development
Classifier: Topic :: Utilities
Classifier: Typing :: Typed
Project-URL: Homepage, http://brainiak.org
Project-URL: Documentation, https://brainiak.org/docs/
Project-URL: Bug tracker, https://github.com/brainiak/brainiak/issues
Project-URL: Changelog, https://brainiak.org/docs/release_notes.html
Project-URL: Chat, https://gitter.im/brainiak/brainiak
Requires-Python: >=3.9
Requires-Dist: numpy>=1.23.5
Requires-Dist: mpi4py>=3
Requires-Dist: nitime
Requires-Dist: scikit-learn>=0.18
Requires-Dist: scipy!=1.0.0
Requires-Dist: statsmodels
Requires-Dist: pymanopt
Requires-Dist: psutil
Requires-Dist: nibabel
Requires-Dist: joblib
Requires-Dist: wheel
Requires-Dist: pydicom
Requires-Dist: pytest; extra == "dev"
Requires-Dist: coverage; extra == "dev"
Requires-Dist: flake8; extra == "dev"
Requires-Dist: flake8-print; extra == "dev"
Requires-Dist: mypy; extra == "dev"
Requires-Dist: myst-nb; extra == "dev"
Requires-Dist: restructuredtext-lint; extra == "dev"
Requires-Dist: setuptools_scm; extra == "dev"
Requires-Dist: sphinx; extra == "dev"
Requires-Dist: sphinx_rtd_theme; extra == "dev"
Requires-Dist: towncrier; extra == "dev"
Requires-Dist: numdifftools; extra == "dev"
Requires-Dist: testbook; extra == "dev"
Requires-Dist: pytest-reportlog; extra == "dev"
Requires-Dist: tensorflow>=2.16; extra == "matnormal"
Requires-Dist: tensorflow_probability[tf]<=0.24.0; extra == "matnormal"
Requires-Dist: nilearn; extra == "examples"
Requires-Dist: nxviz<=0.6.3; extra == "examples"
Requires-Dist: timecorr; extra == "examples"
Requires-Dist: seaborn; extra == "examples"
Requires-Dist: holoviews; extra == "examples"
Requires-Dist: pyOpenSSL; extra == "examples"
Requires-Dist: awscli; extra == "examples"
Requires-Dist: bcrypt; extra == "examples"
Requires-Dist: indexed_gzip; extra == "examples"
Requires-Dist: inflect; extra == "examples"
Requires-Dist: ipython; extra == "examples"
Requires-Dist: jupyter; extra == "examples"
Requires-Dist: mypy; extra == "examples"
Requires-Dist: nibabel; extra == "examples"
Requires-Dist: nilearn; extra == "examples"
Requires-Dist: nodejs; extra == "examples"
Requires-Dist: numpy; extra == "examples"
Requires-Dist: pydicom; extra == "examples"
Requires-Dist: requests; extra == "examples"
Requires-Dist: rpyc; extra == "examples"
Requires-Dist: scikit-learn; extra == "examples"
Requires-Dist: scipy>=1.6.0; extra == "examples"
Requires-Dist: toml; extra == "examples"
Requires-Dist: tornado; extra == "examples"
Requires-Dist: websocket-client; extra == "examples"
Requires-Dist: wsaccel; extra == "examples"
Requires-Dist: inotify; extra == "examples"
Requires-Dist: pybids; extra == "examples"
Requires-Dist: watchdog; extra == "examples"
Requires-Dist: brainiak[dev,examples,matnormal]; extra == "all"
Provides-Extra: dev
Provides-Extra: matnormal
Provides-Extra: examples
Provides-Extra: all
